{"cameraMode":{"drawMode":0,"name":"Shaded","section":"Shading Mode"},"sceneLighting":false,"audioPlay":false,"sceneViewState":{"m_AlwaysRefresh":false,"showFog":true,"showSkybox":false,"showFlares":true,"showImageEffects":true,"showParticleSystems":true,"showVisualEffectGraphs":true,"m_FxEnabled":true},"in2DMode":false,"pivot":{"x":0.43867045640945437,"y":1.4321856498718262,"z":1.107438087463379},"rotation":{"x":0.09881122410297394,"y":-0.6994845271110535,"z":0.1004091128706932,"w":0.7009395360946655},"size":5.496464252471924,"orthographic":false}